{"mc":{
	"fish_22":{
		"frameRate":23,
		"labels":[
			{"name":"act","frame":1,"end":23}
			
			],
		"events":[
			
			],
		"frames":[
			
			{
			"res":"fish_22_1",
			"x":0,
			"y":0
			},
			{
			"res":"fish_22_2",
			"x":0,
			"y":0
			},
			{
			"res":"fish_22_3",
			"x":0,
			"y":0
			},
			{
			"res":"fish_22_4",
			"x":0,
			"y":0
			},
			{
			"res":"fish_22_5",
			"x":0,
			"y":0
			},
			{
			"res":"fish_22_6",
			"x":0,
			"y":0
			},
			{
			"res":"fish_22_7",
			"x":0,
			"y":0
			},
			{
			"res":"fish_22_8",
			"x":0,
			"y":0
			},
			{
			"res":"fish_22_9",
			"x":0,
			"y":0
			},
			{
			"res":"fish_22_10",
			"x":0,
			"y":0
			},
			{
			"res":"fish_22_11",
			"x":0,
			"y":0
			},
			{
			"res":"fish_22_12",
			"x":0,
			"y":0
			},
			{
			"res":"fish_22_13",
			"x":0,
			"y":0
			},
			{
			"res":"fish_22_14",
			"x":0,
			"y":0
			},
			{
			"res":"fish_22_15",
			"x":0,
			"y":0
			},
			{
			"res":"fish_22_16",
			"x":0,
			"y":0
			},
			{
			"res":"fish_22_17",
			"x":0,
			"y":0
			},
			{
			"res":"fish_22_18",
			"x":0,
			"y":0
			},
			{
			"res":"fish_22_19",
			"x":0,
			"y":0
			},
			{
			"res":"fish_22_20",
			"x":0,
			"y":0
			},
			{
			"res":"fish_22_21",
			"x":0,
			"y":0
			},
			{
			"res":"fish_22_22",
			"x":0,
			"y":0
			},
			{
			"res":"fish_22_23",
			"x":0,
			"y":0
			}
			]
}},
	"res":{
		"fish_22_17":{"x":0,"y":620,"w":310,"h":310},
		"fish_22_2":{"x":310,"y":930,"w":310,"h":310},
		"fish_22_19":{"x":310,"y":620,"w":310,"h":310},
		"fish_22_15":{"x":620,"y":310,"w":310,"h":310},
		"fish_22_5":{"x":310,"y":1550,"w":310,"h":310},
		"fish_22_22":{"x":930,"y":310,"w":310,"h":310},
		"fish_22_13":{"x":0,"y":1240,"w":310,"h":310},
		"fish_22_3":{"x":310,"y":310,"w":310,"h":310},
		"fish_22_11":{"x":310,"y":1240,"w":310,"h":310},
		"fish_22_8":{"x":1240,"y":0,"w":310,"h":310},
		"fish_22_7":{"x":1550,"y":0,"w":310,"h":310},
		"fish_22_14":{"x":0,"y":1550,"w":310,"h":310},
		"fish_22_12":{"x":1550,"y":310,"w":310,"h":310},
		"fish_22_21":{"x":620,"y":0,"w":310,"h":310},
		"fish_22_23":{"x":310,"y":0,"w":310,"h":310},
		"fish_22_9":{"x":620,"y":930,"w":310,"h":310},
		"fish_22_6":{"x":930,"y":0,"w":310,"h":310},
		"fish_22_10":{"x":620,"y":620,"w":310,"h":310},
		"fish_22_16":{"x":620,"y":1240,"w":310,"h":310},
		"fish_22_20":{"x":0,"y":930,"w":310,"h":310},
		"fish_22_1":{"x":0,"y":310,"w":310,"h":310},
		"fish_22_4":{"x":0,"y":0,"w":310,"h":310},
		"fish_22_18":{"x":1240,"y":310,"w":310,"h":310}
	}}