{
	"member": [
		{
			"kind": "member",
			"type": "any[]",
			"name": "__frameInfos",
			"memberof": "starlingswf.SwfMovieClip",
			"scope": "instance",
			"pType": "protected",
			"inherited": true,
			"inherits": "starlingswf.SwfMovieClip"
		},
		{
			"kind": "member",
			"type": "Function",
			"name": "_completeFunction",
			"memberof": "starlingswf.SwfMovieClip",
			"scope": "instance",
			"pType": "protected",
			"default": "null",
			"inherited": true,
			"inherits": "starlingswf.SwfMovieClip"
		},
		{
			"kind": "member",
			"type": "number",
			"name": "_currentFrame",
			"memberof": "starlingswf.SwfMovieClip",
			"scope": "instance",
			"pType": "protected",
			"inherited": true,
			"inherits": "starlingswf.SwfMovieClip"
		},
		{
			"kind": "member",
			"type": "string",
			"name": "_currentLabel",
			"memberof": "starlingswf.SwfMovieClip",
			"scope": "instance",
			"pType": "protected",
			"inherited": true,
			"inherits": "starlingswf.SwfMovieClip"
		},
		{
			"kind": "member",
			"type": "Object",
			"name": "_displayObjects",
			"memberof": "starlingswf.SwfMovieClip",
			"scope": "instance",
			"pType": "protected",
			"inherited": true,
			"inherits": "starlingswf.SwfMovieClip"
		},
		{
			"kind": "member",
			"type": "number",
			"name": "_endFrame",
			"memberof": "starlingswf.SwfMovieClip",
			"scope": "instance",
			"pType": "protected",
			"inherited": true,
			"inherits": "starlingswf.SwfMovieClip"
		},
		{
			"kind": "member",
			"type": "any[]",
			"name": "_frames",
			"memberof": "starlingswf.SwfMovieClip",
			"scope": "instance",
			"pType": "protected",
			"inherited": true,
			"inherits": "starlingswf.SwfMovieClip"
		},
		{
			"kind": "member",
			"type": "boolean",
			"name": "_isPlay",
			"memberof": "starlingswf.SwfMovieClip",
			"scope": "instance",
			"pType": "protected",
			"default": "false",
			"inherited": true,
			"inherits": "starlingswf.SwfMovieClip"
		},
		{
			"kind": "member",
			"type": "any[]",
			"name": "_labels",
			"memberof": "starlingswf.SwfMovieClip",
			"scope": "instance",
			"pType": "protected",
			"inherited": true,
			"inherits": "starlingswf.SwfMovieClip"
		},
		{
			"kind": "member",
			"type": "starlingswf.Swf",
			"name": "_ownerSwf",
			"memberof": "starlingswf.SwfMovieClip",
			"scope": "instance",
			"pType": "protected",
			"inherited": true,
			"inherits": "starlingswf.SwfMovieClip"
		},
		{
			"kind": "member",
			"type": "number",
			"name": "_startFrame",
			"memberof": "starlingswf.SwfMovieClip",
			"scope": "instance",
			"pType": "protected",
			"inherited": true,
			"inherits": "starlingswf.SwfMovieClip"
		},
		{
			"kind": "member",
			"type": "boolean",
			"name": "loop",
			"memberof": "starlingswf.SwfMovieClip",
			"scope": "instance",
			"pType": "public",
			"default": "true",
			"inherited": true,
			"inherits": "starlingswf.SwfMovieClip"
		}
	],
	"function": [
		{
			"kind": "function",
			"name": "StarlingSwfMovieClip",
			"memberof": "StarlingSwfMovieClip",
			"scope": "instance",
			"description": "构造函数",
			"params": [
				{
					"name": "frames",
					"type": "any[]",
					"description": "frames"
				},
				{
					"name": "labels",
					"type": "any[]",
					"description": "labels"
				},
				{
					"name": "displayObjects",
					"type": "Object",
					"description": "displayObjects"
				},
				{
					"name": "ownerSwf",
					"type": "starlingswf.Swf",
					"description": "ownerSwf"
				}
			],
			"pType": "public"
		},
		{
			"kind": "function",
			"type": "string",
			"name": "currentLabel",
			"memberof": "starlingswf.SwfMovieClip",
			"scope": "instance",
			"description": "返回当前播放的是哪一个标签",
			"pType": "public",
			"inherited": true,
			"inherits": "starlingswf.SwfMovieClip"
		},
		{
			"kind": "function",
			"type": "void",
			"name": "dispose",
			"memberof": "StarlingSwfMovieClip",
			"scope": "instance",
			"description": "销毁",
			"pType": "public"
		},
		{
			"kind": "function",
			"type": "number",
			"name": "getCurrentFrame",
			"memberof": "starlingswf.SwfMovieClip",
			"scope": "instance",
			"pType": "public",
			"inherited": true,
			"inherits": "starlingswf.SwfMovieClip"
		},
		{
			"kind": "function",
			"type": "egret.Bitmap",
			"name": "getImage",
			"memberof": "starlingswf.SwfSprite",
			"scope": "instance",
			"params": [
				{
					"name": "name",
					"type": "string",
					"description": ""
				}
			],
			"pType": "public",
			"inherited": true,
			"inherits": "starlingswf.SwfSprite"
		},
		{
			"kind": "function",
			"type": "number",
			"name": "getLabelEndFrame",
			"memberof": "starlingswf.SwfMovieClip",
			"scope": "instance",
			"description": "获取某一标签的结束帧",
			"returns": "",
			"params": [
				{
					"name": "label",
					"type": "string",
					"description": "label"
				}
			],
			"pType": "public",
			"inherited": true,
			"inherits": "starlingswf.SwfMovieClip"
		},
		{
			"kind": "function",
			"type": "number",
			"name": "getLabelStartFrame",
			"memberof": "starlingswf.SwfMovieClip",
			"scope": "instance",
			"description": "以下为扩展代码",
			"params": [
				{
					"name": "label",
					"type": "string",
					"description": ""
				}
			],
			"pType": "public",
			"inherited": true,
			"inherits": "starlingswf.SwfMovieClip"
		},
		{
			"kind": "function",
			"type": "starlingswf.SwfMovieClip",
			"name": "getMovie",
			"memberof": "starlingswf.SwfSprite",
			"scope": "instance",
			"params": [
				{
					"name": "name",
					"type": "string",
					"description": ""
				}
			],
			"pType": "public",
			"inherited": true,
			"inherits": "starlingswf.SwfSprite"
		},
		{
			"kind": "function",
			"type": "starlingswf.SwfSprite",
			"name": "getSprite",
			"memberof": "starlingswf.SwfSprite",
			"scope": "instance",
			"params": [
				{
					"name": "name",
					"type": "string",
					"description": ""
				}
			],
			"pType": "public",
			"inherited": true,
			"inherits": "starlingswf.SwfSprite"
		},
		{
			"kind": "function",
			"type": "egret.TextField",
			"name": "getTextField",
			"memberof": "starlingswf.SwfSprite",
			"scope": "instance",
			"params": [
				{
					"name": "name",
					"type": "string",
					"description": ""
				}
			],
			"pType": "public",
			"inherited": true,
			"inherits": "starlingswf.SwfSprite"
		},
		{
			"kind": "function",
			"type": "void",
			"name": "goToPlay",
			"memberof": "StarlingSwfMovieClip",
			"scope": "instance",
			"description": "播放",
			"params": [
				{
					"name": "frame",
					"type": "Object",
					"description": "frame"
				}
			],
			"pType": "public"
		},
		{
			"kind": "function",
			"type": "void",
			"name": "gotoAndPlay",
			"memberof": "starlingswf.SwfMovieClip",
			"scope": "instance",
			"params": [
				{
					"name": "frame",
					"type": "Object",
					"description": ""
				}
			],
			"pType": "public",
			"inherited": true,
			"inherits": "starlingswf.SwfMovieClip"
		},
		{
			"kind": "function",
			"type": "void",
			"name": "gotoAndStop",
			"memberof": "starlingswf.SwfMovieClip",
			"scope": "instance",
			"params": [
				{
					"name": "frame",
					"type": "Object",
					"description": ""
				},
				{
					"name": "stopChild",
					"type": "boolean",
					"default": "true",
					"description": ""
				}
			],
			"pType": "public",
			"inherited": true,
			"inherits": "starlingswf.SwfMovieClip"
		},
		{
			"kind": "function",
			"type": "Boolean",
			"name": "hasLabel",
			"memberof": "starlingswf.SwfMovieClip",
			"scope": "instance",
			"description": "是否包含某个标签",
			"params": [
				{
					"name": "label",
					"type": "String",
					"description": ""
				}
			],
			"pType": "public",
			"inherited": true,
			"inherits": "starlingswf.SwfMovieClip"
		},
		{
			"kind": "function",
			"type": "boolean",
			"name": "isPlay",
			"memberof": "starlingswf.SwfMovieClip",
			"scope": "instance",
			"description": "是否再播放",
			"pType": "public",
			"inherited": true,
			"inherits": "starlingswf.SwfMovieClip"
		},
		{
			"kind": "function",
			"type": "any[]",
			"name": "labels",
			"memberof": "starlingswf.SwfMovieClip",
			"scope": "instance",
			"description": "获取所有标签",
			"pType": "public",
			"inherited": true,
			"inherits": "starlingswf.SwfMovieClip"
		},
		{
			"kind": "function",
			"type": "void",
			"name": "play",
			"memberof": "starlingswf.SwfMovieClip",
			"scope": "instance",
			"description": "播放",
			"pType": "public",
			"inherited": true,
			"inherits": "starlingswf.SwfMovieClip"
		},
		{
			"kind": "function",
			"type": "void",
			"name": "setCompleteAction",
			"memberof": "StarlingSwfMovieClip",
			"scope": "instance",
			"description": "设置mc播放完成执行的函数",
			"params": [
				{
					"name": "$action",
					"type": "Function",
					"description": "执行函数"
				},
				{
					"name": "$actionObj",
					"type": "any",
					"description": "执行函数所属对象"
				}
			],
			"pType": "public"
		},
		{
			"kind": "function",
			"type": "void",
			"name": "setCurrentFrame",
			"memberof": "StarlingSwfMovieClip",
			"scope": "instance",
			"description": "重写setCurrentFrame函数，处理帧事件",
			"params": [
				{
					"name": "frame",
					"type": "number",
					"description": ""
				}
			],
			"pType": "public"
		},
		{
			"kind": "function",
			"type": "void",
			"name": "setFrameAction",
			"memberof": "StarlingSwfMovieClip",
			"scope": "instance",
			"description": "设置帧事件",
			"params": [
				{
					"name": "$frame",
					"type": "number",
					"description": "第几帧"
				},
				{
					"name": "$action",
					"type": "Function",
					"description": "执行函数"
				},
				{
					"name": "$actionObj",
					"type": "any",
					"description": "执行函数所属对象"
				},
				{
					"name": "$param",
					"type": "any",
					"default": "null",
					"description": "执行函数所需参数"
				}
			],
			"pType": "public"
		},
		{
			"kind": "function",
			"type": "void",
			"name": "stop",
			"memberof": "starlingswf.SwfMovieClip",
			"scope": "instance",
			"description": "停止",
			"params": [
				{
					"name": "stopChild",
					"type": "boolean",
					"default": "true",
					"description": "是否停止子动画"
				}
			],
			"pType": "public",
			"inherited": true,
			"inherits": "starlingswf.SwfMovieClip"
		},
		{
			"kind": "function",
			"type": "number",
			"name": "totalFrames",
			"memberof": "starlingswf.SwfMovieClip",
			"scope": "instance",
			"description": "总共有多少帧",
			"pType": "public",
			"inherited": true,
			"inherits": "starlingswf.SwfMovieClip"
		},
		{
			"kind": "function",
			"type": "void",
			"name": "update",
			"memberof": "starlingswf.SwfMovieClip",
			"scope": "instance",
			"pType": "public",
			"inherited": true,
			"inherits": "starlingswf.SwfMovieClip"
		}
	],
	"globalMember": [],
	"globalFunction": [],
	"class": {
		"kind": "class",
		"name": "StarlingSwfMovieClip",
		"memberof": "",
		"filename": "D:\\Project\\白鹭H5电玩城\\h5-client\\src\\core\\starlingswf\\game\\StarlingSwfMovieClip.ts",
		"description": "Created by yangsong on 2014/6/16.自定义SwfMovieClip类，带有帧处理函数",
		"augments": [
			"starlingswf.SwfMovieClip",
			"starlingswf.SwfSprite"
		]
	},
	"pType": "public"
}